{"Plot": "Young boy befriends larcenous orangutan in luxury hotel.", "Rated": "PG", "Response": "True", "Language": "English, French", "Title": "Dunston Checks In", "Country": "USA", "Writer": "John Hopkins (story), John Hopkins (screenplay), Bruce Graham (screenplay)", "Metascore": "N/A", "imdbRating": "5.2", "Director": "Ken Kwapis", "Released": "12 Jan 1996", "Actors": "Jason Alexander, Faye Dunaway, Eric Lloyd, Rupert Everett", "Year": "1996", "Genre": "Comedy, Adventure, Family", "Awards": "4 nominations.", "Runtime": "88 min", "Type": "movie", "Poster": "http://ia.media-imdb.com/images/M/MV5BMTM2OTI4ODAxMl5BMl5BanBnXkFtZTcwODUzMzYyMQ@@._V1_SX300.jpg", "imdbVotes": "9,635", "imdbID": "tt0116151"}