{"Plot": "Young, wild poet Arthur Rimbaud and his mentor Paul Verlaine engage in a fierce, forbidden romance while feeling the effects of a hellish artistic lifestyle.", "Rated": "R", "Response": "True", "Language": "English", "Title": "Total Eclipse", "Country": "UK, France, Belgium", "Writer": "Christopher Hampton (screenplay)", "Metascore": "N/A", "imdbRating": "6.5", "Director": "Agnieszka Holland", "Released": "03 Nov 1995", "Actors": "Leonardo DiCaprio, David Thewlis, Romane Bohringer, Dominique Blanc", "Year": "1995", "Genre": "Biography, Drama, Romance", "Awards": "1 nomination.", "Runtime": "111 min", "Type": "movie", "Poster": "http://ia.media-imdb.com/images/M/MV5BMjEyMTY0NDM2N15BMl5BanBnXkFtZTcwMjMzNDYxMQ@@._V1_SX300.jpg", "imdbVotes": "10,199", "imdbID": "tt0114702"}