{"Plot": "A family of Irish immigrants adjust to life on the mean streets of Hell's Kitchen while also grieving the death of a child.", "Rated": "PG-13", "Response": "True", "Language": "English, Spanish, Irish", "Title": "In America", "Country": "Ireland, UK", "Writer": "Jim Sheridan, Naomi Sheridan, Kirsten Sheridan", "Metascore": "76", "imdbRating": "7.8", "Director": "Jim Sheridan", "Released": "06 Feb 2004", "Actors": "Paddy Considine, Samantha Morton, Sarah Bolger, Emma Bolger", "Year": "2002", "Genre": "Drama", "Awards": "Nominated for 3 Oscars. Another 27 wins & 55 nominations.", "Runtime": "105 min", "Type": "movie", "Poster": "http://ia.media-imdb.com/images/M/MV5BMTU0NTkwMTEzM15BMl5BanBnXkFtZTcwOTQ3MzQyMQ@@._V1_SX300.jpg", "imdbVotes": "36,305", "imdbID": "tt0298845"}