{"Plot": "An evil millionaire believes he is Santa Claus after an accident renders him amnesiac.", "Rated": "PG", "Response": "True", "Language": "English", "Title": "Santa with Muscles", "Country": "USA", "Writer": "Jonathan Bond (screenplay), Fred Mata (screenplay), Dorrie Krum Raymond (screenplay)", "Metascore": "N/A", "imdbRating": "2.4", "Director": "John Murlowski", "Released": "08 Nov 1996", "Actors": "Hulk Hogan, Don Stark, Robin Curtis, Garrett Morris", "Year": "1996", "Genre": "Family, Comedy", "Awards": "N/A", "Runtime": "97 min", "Type": "movie", "Poster": "http://ia.media-imdb.com/images/M/MV5BMTBkNmZhZGUtMzkyNi00ZThhLTg1YmQtMzUyNjA3MzA3MTAxXkEyXkFqcGdeQXVyNjA3OTI5MjA@._V1_SX300.jpg", "imdbVotes": "7,730", "imdbID": "tt0117550"}