{"Plot": "True story of an attractive Sicilian mob-wife who participates in her husband's drug-dealing business and falls for her husband's lackey.", "Rated": "R", "Response": "True", "Language": "Italian", "Title": "Angela", "Country": "Italy", "Writer": "Massimo D'Anolfi (screenplay), Roberta Torre", "Metascore": "N/A", "imdbRating": "6.1", "Director": "Roberta Torre", "Released": "30 Oct 2002", "Actors": "Donatella Finocchiaro, Andrea Di Stefano, Mario Pupella, Toni Gambino", "Year": "2002", "Genre": "Crime, Drama, Romance", "Awards": "4 wins & 8 nominations.", "Runtime": "95 min", "Type": "movie", "Poster": "http://ia.media-imdb.com/images/M/MV5BMTM2ODg3MDkzMV5BMl5BanBnXkFtZTcwMDMzOTQyMQ@@._V1_SX300.jpg", "imdbVotes": "258", "imdbID": "tt0287914"}