{"Plot": "Photographer Robert Kincaid wanders into the life of housewife Francesca Johnson, for four days in the 1960s.", "Rated": "PG-13", "Response": "True", "Language": "English", "Title": "The Bridges of Madison County", "Country": "USA", "Writer": "Richard LaGravenese (screenplay), Robert James Waller (novel)", "Metascore": "66", "imdbRating": "7.5", "Director": "Clint Eastwood", "Released": "02 Jun 1995", "Actors": "Clint Eastwood, Meryl Streep, Annie Corley, Victor Slezak", "Year": "1995", "Genre": "Drama, Romance", "Awards": "Nominated for 1 Oscar. Another 6 wins & 14 nominations.", "Runtime": "135 min", "Type": "movie", "Poster": "http://ia.media-imdb.com/images/M/MV5BMTI0MDkxMzA2NF5BMl5BanBnXkFtZTYwNjIxMDI5._V1_SX300.jpg", "imdbVotes": "53,591", "imdbID": "tt0112579"}