{"Plot": "A man on the run is hunted by a demon known as the Collector.", "Rated": "R", "Response": "True", "Language": "English", "Title": "Tales from the Crypt: Demon Knight", "Country": "USA", "Writer": "Ethan Reiff, Cyrus Voris, Mark Bishop", "Metascore": "N/A", "imdbRating": "6.7", "Director": "Ernest R. Dickerson", "Released": "13 Jan 1995", "Actors": "John Kassir, Billy Zane, William Sadler, Jada Pinkett Smith", "Year": "1995", "Genre": "Action, Fantasy, Horror", "Awards": "1 nomination.", "Runtime": "92 min", "Type": "movie", "Poster": "http://ia.media-imdb.com/images/M/MV5BMTkzOTY2MDUzMV5BMl5BanBnXkFtZTcwNTIyOTgyMQ@@._V1_SX300.jpg", "imdbVotes": "16,347", "imdbID": "tt0114608"}