{"Plot": "Ridiculed because of his enormous ears, a young circus elephant is assisted by a mouse to achieve his full potential.", "Rated": "APPROVED", "Response": "True", "Language": "English", "Title": "Dumbo", "Country": "USA", "Writer": "Joe Grant (screen story), Dick Huemer (screen story), Otto Englander (story direction), Bill Peet (story development), Aurelius Battaglia (story development), Joe Rinaldi (story development), Vernon Stallings (story development), Webb Smith (story development)", "Metascore": "N/A", "imdbRating": "7.3", "Director": "Samuel Armstrong, Norman Ferguson, Wilfred Jackson, Jack Kinney, Bill Roberts, Ben Sharpsteen, John Elliotte", "Released": "31 Oct 1941", "Actors": "James Baskett, Herman Bing, Billy Bletcher, Edward Brophy", "Year": "1941", "Genre": "Animation, Drama, Family", "Awards": "Won 1 Oscar. Another 2 wins & 1 nomination.", "Runtime": "64 min", "Type": "movie", "Poster": "http://ia.media-imdb.com/images/M/MV5BMjIyNDg3NDMwMl5BMl5BanBnXkFtZTgwNjI0Njg0MTE@._V1._CR23,22,947,1455_SX89_AL_.jpg_V1_SX300.jpg", "imdbVotes": "82,925", "imdbID": "tt0033563"}