{"Plot": "Maggie's and Sam's former partners are in love; she wants revenge and he wants his lost love back, so they work together to break up the happy couple.", "Rated": "R", "Response": "True", "Language": "English, French", "Title": "Addicted to Love", "Country": "USA", "Writer": "Robert Gordon", "Metascore": "49", "imdbRating": "6.1", "Director": "Griffin Dunne", "Released": "23 May 1997", "Actors": "Meg Ryan, Matthew Broderick, Kelly Preston, Tch\u00e9ky Karyo", "Year": "1997", "Genre": "Comedy, Romance", "Awards": "1 nomination.", "Runtime": "100 min", "Type": "movie", "Poster": "http://ia.media-imdb.com/images/M/MV5BMTU5MjA3ODA3MV5BMl5BanBnXkFtZTcwNTgyNTUyMQ@@._V1_SX300.jpg", "imdbVotes": "19,506", "imdbID": "tt0118556"}