{"Plot": "Joe and Lucy are roommates and best friends. Lucy, whose love life is embarrassingly dull, convinces Joe, who is infatuated with a neighbor he's never met, that if they don't have stable ...", "Rated": "R", "Response": "True", "Language": "English", "Title": "If Lucy Fell", "Country": "USA", "Writer": "Eric Schaeffer (story), Tony Spiridakis (story), Eric Schaeffer (screenplay)", "Metascore": "N/A", "imdbRating": "4.9", "Director": "Eric Schaeffer", "Released": "08 Mar 1996", "Actors": "Sarah Jessica Parker, Eric Schaeffer, Ben Stiller, Elle Macpherson", "Year": "1996", "Genre": "Comedy, Romance", "Awards": "N/A", "Runtime": "92 min", "Type": "movie", "Poster": "http://ia.media-imdb.com/images/M/MV5BMTIyNjYyMjIyMV5BMl5BanBnXkFtZTcwNzE4OTUxMQ@@._V1_SX300.jpg", "imdbVotes": "3,332", "imdbID": "tt0116606"}