{"Plot": "Twenty-two year old Chinese-Canadian Jade Li comes from a traditional Chinese family, who try to put on the perfect public persona at all cost so as to \"save face\". One primary part of this...", "Rated": "PG-13", "Response": "True", "Language": "English, Cantonese", "Title": "Double Happiness", "Country": "Canada", "Writer": "Mina Shum", "Metascore": "N/A", "imdbRating": "7.2", "Director": "Mina Shum", "Released": "28 Jul 1995", "Actors": "Sandra Oh, Stephen Chang, Alannah Ong, Donald Fong", "Year": "1994", "Genre": "Drama", "Awards": "6 wins & 6 nominations.", "Runtime": "87 min", "Type": "movie", "Poster": "http://ia.media-imdb.com/images/M/MV5BMjE2MjI3NjQzNV5BMl5BanBnXkFtZTcwNzMzOTE0MQ@@._V1_SX300.jpg", "imdbVotes": "920", "imdbID": "tt0109655"}