{"Plot": "A story about the ins and outs of one unusual health facility in the early 20th century, run by the eccentric Dr. Kellogg.", "Rated": "R", "Response": "True", "Language": "English", "Title": "The Road to Wellville", "Country": "USA", "Writer": "T. Coraghessan Boyle (novel), Alan Parker (screenplay)", "Metascore": "N/A", "imdbRating": "5.7", "Director": "Alan Parker", "Released": "28 Oct 1994", "Actors": "Anthony Hopkins, Bridget Fonda, Matthew Broderick, John Cusack", "Year": "1994", "Genre": "Comedy, Drama", "Awards": "3 nominations.", "Runtime": "118 min", "Type": "movie", "Poster": "http://ia.media-imdb.com/images/M/MV5BMTg0MDc4NTY5N15BMl5BanBnXkFtZTcwMzU1NTYyMQ@@._V1_SX300.jpg", "imdbVotes": "9,622", "imdbID": "tt0111001"}