{"Plot": "Wally Sparks is a tabloid TV show reporter who's trying to boost ratings on his show. He goes to the governor's mansion to uncover a sex scandal.", "Rated": "R", "Response": "True", "Language": "English", "Title": "Meet Wally Sparks", "Country": "USA", "Writer": "Harry Basil (story), Rodney Dangerfield (screenplay), Harry Basil (screenplay)", "Metascore": "N/A", "imdbRating": "5.1", "Director": "Peter Baldwin", "Released": "31 Jan 1997", "Actors": "Rodney Dangerfield, Debi Mazar, David Ogden Stiers, Burt Reynolds", "Year": "1997", "Genre": "Comedy", "Awards": "N/A", "Runtime": "105 min", "Type": "movie", "Poster": "http://ia.media-imdb.com/images/M/MV5BMTM2MjM0NjA3NV5BMl5BanBnXkFtZTcwOTYxNzIyMQ@@._V1_SX300.jpg", "imdbVotes": "2,408", "imdbID": "tt0119644"}