{"Plot": "Roger uses his son Igor to ruthlessly traffic and exploit illegal aliens. When one of the aliens is killed, Igor is guilt-ridden and wants to care for the dead man's family against his father's orders.", "Rated": "NOT RATED", "Response": "True", "Language": "French, Romanian", "Title": "La Promesse", "Country": "Belgium, France, Luxembourg, Tunisia", "Writer": "Luc Dardenne, Jean-Pierre Dardenne", "Metascore": "82", "imdbRating": "7.9", "Director": "Jean-Pierre Dardenne, Luc Dardenne", "Released": "16 May 1997", "Actors": "J\u00e9r\u00e9mie Renier, Olivier Gourmet, Assita Ouedraogo, Jean-Michel Balthazar", "Year": "1996", "Genre": "Drama", "Awards": "16 wins & 5 nominations.", "Runtime": "90 min", "Type": "movie", "Poster": "http://ia.media-imdb.com/images/M/MV5BMTkxODcwMjg0MF5BMl5BanBnXkFtZTcwOTExNTIyMQ@@._V1_SX300.jpg", "imdbVotes": "5,058", "imdbID": "tt0117398"}