{"Plot": "After a bizarre encounter at a party, a jazz saxophonist is framed for the murder of his wife and sent to prison, where he inexplicably morphs into a young mechanic and begins leading a new life.", "Rated": "R", "Response": "True", "Language": "English", "Title": "Lost Highway", "Country": "France, USA", "Writer": "David Lynch, Barry Gifford", "Metascore": "52", "imdbRating": "7.6", "Director": "David Lynch", "Released": "21 Feb 1997", "Actors": "Bill Pullman, Patricia Arquette, John Roselius, Louis Eppolito", "Year": "1997", "Genre": "Mystery, Thriller", "Awards": "1 win.", "Runtime": "134 min", "Type": "movie", "Poster": "http://ia.media-imdb.com/images/M/MV5BMTk3MzUxOTQyNF5BMl5BanBnXkFtZTgwODM3Mjc1MDE@._V1_SX300.jpg", "imdbVotes": "95,564", "imdbID": "tt0116922"}