{"Plot": "Jeffrey, a young gay man in New York, decides that sex is too much and decided to become celibate. He immediately meets the man of his dreams and must decide whether or not love is worth ...", "Rated": "R", "Response": "True", "Language": "English", "Title": "Jeffrey", "Country": "USA", "Writer": "Paul Rudnick (play), Paul Rudnick (screenplay)", "Metascore": "N/A", "imdbRating": "6.7", "Director": "Christopher Ashley", "Released": "18 Aug 1995", "Actors": "Steven Weber, Peter Jacobson, Tom Cayler, David Thornton", "Year": "1995", "Genre": "Comedy, Drama", "Awards": "1 win & 4 nominations.", "Runtime": "92 min", "Type": "movie", "Poster": "http://ia.media-imdb.com/images/M/MV5BMTc4MjM1Njc3NF5BMl5BanBnXkFtZTcwNzI0OTgyMQ@@._V1_SX300.jpg", "imdbVotes": "4,856", "imdbID": "tt0113464"}