{"Plot": "Two stumblebum inheritors are determined to rid their antique house of a mouse who is equally determined to stay where he is.", "Rated": "PG", "Response": "True", "Language": "English", "Title": "Mousehunt", "Country": "USA", "Writer": "Adam Rifkin", "Metascore": "54", "imdbRating": "6.4", "Director": "Gore Verbinski", "Released": "19 Dec 1997", "Actors": "Nathan Lane, Lee Evans, Vicki Lewis, Maury Chaykin", "Year": "1997", "Genre": "Comedy, Family", "Awards": "2 wins & 2 nominations.", "Runtime": "98 min", "Type": "movie", "Poster": "http://ia.media-imdb.com/images/M/MV5BMTk1MDExMTA5NF5BMl5BanBnXkFtZTcwOTMzNTIyMQ@@._V1_SX300.jpg", "imdbVotes": "40,722", "imdbID": "tt0119715"}