{"Plot": "A convicted rapist, released from prison after serving a fourteen-year sentence, stalks the family of the lawyer who originally defended him.", "Rated": "R", "Response": "True", "Language": "English", "Title": "Cape Fear", "Country": "USA", "Writer": "John D. MacDonald (novel), James R. Webb (earlier screenplay), Wesley Strick (screenplay)", "Metascore": "73", "imdbRating": "7.3", "Director": "Martin Scorsese", "Released": "15 Nov 1991", "Actors": "Robert De Niro, Nick Nolte, Jessica Lange, Juliette Lewis", "Year": "1991", "Genre": "Crime, Thriller", "Awards": "Nominated for 2 Oscars. Another 4 wins & 14 nominations.", "Runtime": "128 min", "Type": "movie", "Poster": "http://ia.media-imdb.com/images/M/MV5BMjE0NDE2MDI2MF5BMl5BanBnXkFtZTgwOTU2Mzk5MDE@._V1_SX300.jpg", "imdbVotes": "123,527", "imdbID": "tt0101540"}