{"Plot": "When Manny Singer's wife dies, his young daughter Molly becomes mute and withdrawn. To help cope with looking after Molly, he hires sassy housekeeper Corrina Washington, who coaxes Molly ...", "Rated": "PG", "Response": "True", "Language": "English", "Title": "Corrina, Corrina", "Country": "USA", "Writer": "Jessie Nelson", "Metascore": "N/A", "imdbRating": "6.5", "Director": "Jessie Nelson", "Released": "26 Aug 1994", "Actors": "Noreen Hennessey, Lucy Webb, Erica Yohn, Tina Majorino", "Year": "1994", "Genre": "Comedy, Drama, Romance", "Awards": "2 nominations.", "Runtime": "115 min", "Type": "movie", "Poster": "http://ia.media-imdb.com/images/M/MV5BMTI2MTM0MjE1Nl5BMl5BanBnXkFtZTcwOTcwMzEyMQ@@._V1_SX300.jpg", "imdbVotes": "9,774", "imdbID": "tt0109484"}