{"Plot": "Two childhood friends find themselves forced to become enemies.", "Rated": "G", "Response": "True", "Language": "English", "Title": "The Fox and the Hound", "Country": "USA", "Writer": "Daniel P. Mannix (based on the book by), Larry Clemmons (story), Ted Berman (story), David Michener (story), Peter Young (story), Burny Mattinson (story), Steve Hulett (story), Earl Kress (story), Vance Gerry (story)", "Metascore": "N/A", "imdbRating": "7.3", "Director": "Ted Berman, Richard Rich, Art Stevens", "Released": "10 Jul 1981", "Actors": "Mickey Rooney, Kurt Russell, Pearl Bailey, Jack Albertson", "Year": "1981", "Genre": "Animation, Adventure, Drama", "Awards": "1 win & 2 nominations.", "Runtime": "83 min", "Type": "movie", "Poster": "http://ia.media-imdb.com/images/M/MV5BMTQ3Njc0MjU4NF5BMl5BanBnXkFtZTcwMzcxMzUzMQ@@._V1_SX300.jpg", "imdbVotes": "61,723", "imdbID": "tt0082406"}