{"Plot": "The two top agents of the United Network Command for Law and Enforcement fight the enemies of peace, particularly the forces of THRUSH.", "Rated": "N/A", "Response": "True", "Language": "English", "Title": "The Man from U.N.C.L.E.", "Country": "USA", "Writer": "Sam Rolfe", "Metascore": "N/A", "imdbRating": "7.8", "Director": "N/A", "Released": "22 Sep 1964", "Actors": "Robert Vaughn, David McCallum, Leo G. Carroll", "Year": "1964\u20131968", "Genre": "Action, Adventure, Crime", "Awards": "Won 1 Golden Globe. Another 1 win & 22 nominations.", "Runtime": "50 min", "Type": "series", "Poster": "http://ia.media-imdb.com/images/M/MV5BMTg0NDgwMzU1Ml5BMl5BanBnXkFtZTgwOTY5MDkwMzE@._V1._CR88,0,326,373_SY132_CR13,0,89,132_AL_.jpg_V1_SX300.jpg", "imdbVotes": "3,061", "imdbID": "tt0057765"}